[
  {
    "text": "musulman",
    "size": 12667
  },
  {
    "text": "burkina",
    "size": 8724
  },
  {
    "text": "pays",
    "size": 5547
  },
  {
    "text": "dieu",
    "size": 5232
  },
  {
    "text": "faso",
    "size": 5130
  },
  {
    "text": "hadj",
    "size": 5066
  },
  {
    "text": "islam",
    "size": 5012
  },
  {
    "text": "communauté",
    "size": 4874
  },
  {
    "text": "islamique",
    "size": 4648
  },
  {
    "text": "jour",
    "size": 4599
  },
  {
    "text": "président",
    "size": 4337
  },
  {
    "text": "grand",
    "size": 4259
  },
  {
    "text": "prière",
    "size": 4220
  },
  {
    "text": "paix",
    "size": 4105
  },
  {
    "text": "mois",
    "size": 3974
  },
  {
    "text": "religieux",
    "size": 3883
  },
  {
    "text": "burkinabè",
    "size": 3698
  },
  {
    "text": "national",
    "size": 3684
  },
  {
    "text": "bien",
    "size": 3549
  },
  {
    "text": "fidèle",
    "size": 3548
  },
  {
    "text": "ouagadougou",
    "size": 3486
  },
  {
    "text": "prendre",
    "size": 3454
  },
  {
    "text": "venir",
    "size": 3349
  },
  {
    "text": "mosquée",
    "size": 3302
  },
  {
    "text": "jeûne",
    "size": 3271
  },
  {
    "text": "homme",
    "size": 3246
  },
  {
    "text": "année",
    "size": 3185
  },
  {
    "text": "bon",
    "size": 3093
  },
  {
    "text": "imam",
    "size": 3071
  },
  {
    "text": "association",
    "size": 3069
  },
  {
    "text": "prophète",
    "size": 2977
  },
  {
    "text": "etat",
    "size": 2974
  },
  {
    "text": "pèlerin",
    "size": 2952
  },
  {
    "text": "femme",
    "size": 2945
  },
  {
    "text": "ministre",
    "size": 2859
  },
  {
    "text": "organisation",
    "size": 2851
  },
  {
    "text": "dernier",
    "size": 2840
  },
  {
    "text": "religion",
    "size": 2796
  },
  {
    "text": "fête",
    "size": 2742
  },
  {
    "text": "ramadan",
    "size": 2650
  },
  {
    "text": "lieu",
    "size": 2581
  },
  {
    "text": "social",
    "size": 2488
  },
  {
    "text": "monde",
    "size": 2431
  },
  {
    "text": "allah",
    "size": 2422
  },
  {
    "text": "coran",
    "size": 2381
  },
  {
    "text": "devoir",
    "size": 2371
  },
  {
    "text": "mettre",
    "size": 2287
  },
  {
    "text": "donner",
    "size": 2231
  },
  {
    "text": "place",
    "size": 2175
  },
  {
    "text": "politique",
    "size": 2134
  },
  {
    "text": "général",
    "size": 2067
  },
  {
    "text": "vie",
    "size": 2051
  },
  {
    "text": "membre",
    "size": 2020
  },
  {
    "text": "nuit",
    "size": 1951
  },
  {
    "text": "permettre",
    "size": 1946
  },
  {
    "text": "population",
    "size": 1913
  },
  {
    "text": "question",
    "size": 1912
  },
  {
    "text": "autorité",
    "size": 1900
  },
  {
    "text": "enfant",
    "size": 1899
  },
  {
    "text": "chef",
    "size": 1889
  },
  {
    "text": "an",
    "size": 1882
  },
  {
    "text": "vivre",
    "size": 1880
  },
  {
    "text": "ouédraogo",
    "size": 1871
  },
  {
    "text": "ensemble",
    "size": 1848
  },
  {
    "text": "non",
    "size": 1844
  },
  {
    "text": "pèlerinage",
    "size": 1791
  },
  {
    "text": "sécurité",
    "size": 1757
  },
  {
    "text": "passer",
    "size": 1748
  },
  {
    "text": "famille",
    "size": 1716
  },
  {
    "text": "temps",
    "size": 1690
  },
  {
    "text": "gouvernement",
    "size": 1665
  },
  {
    "text": "action",
    "size": 1628
  },
  {
    "text": "jeune",
    "size": 1626
  },
  {
    "text": "acte",
    "size": 1610
  },
  {
    "text": "occasion",
    "size": 1602
  },
  {
    "text": "développement",
    "size": 1575
  },
  {
    "text": "formation",
    "size": 1565
  },
  {
    "text": "connaître",
    "size": 1547
  },
  {
    "text": "fin",
    "size": 1536
  },
  {
    "text": "saint",
    "size": 1526
  },
  {
    "text": "responsable",
    "size": 1522
  },
  {
    "text": "demander",
    "size": 1516
  },
  {
    "text": "situation",
    "size": 1510
  },
  {
    "text": "école",
    "size": 1502
  },
  {
    "text": "société",
    "size": 1487
  },
  {
    "text": "moment",
    "size": 1486
  },
  {
    "text": "mecque",
    "size": 1481
  },
  {
    "text": "trouver",
    "size": 1475
  },
  {
    "text": "chose",
    "size": 1451
  },
  {
    "text": "travers",
    "size": 1451
  },
  {
    "text": "foi",
    "size": 1449
  },
  {
    "text": "problème",
    "size": 1438
  },
  {
    "text": "fois",
    "size": 1436
  },
  {
    "text": "groupe",
    "size": 1434
  },
  {
    "text": "travail",
    "size": 1433
  },
  {
    "text": "heure",
    "size": 1426
  },
  {
    "text": "organiser",
    "size": 1418
  },
  {
    "text": "droit",
    "size": 1414
  },
  {
    "text": "beaucoup",
    "size": 1377
  },
  {
    "text": "cours",
    "size": 1370
  },
  {
    "text": "cas",
    "size": 1361
  },
  {
    "text": "force",
    "size": 1357
  },
  {
    "text": "appeler",
    "size": 1356
  },
  {
    "text": "activité",
    "size": 1352
  },
  {
    "text": "agir",
    "size": 1342
  },
  {
    "text": "point",
    "size": 1325
  },
  {
    "text": "prier",
    "size": 1309
  },
  {
    "text": "région",
    "size": 1304
  },
  {
    "text": "souhaiter",
    "size": 1292
  },
  {
    "text": "affaire",
    "size": 1282
  },
  {
    "text": "nom",
    "size": 1282
  },
  {
    "text": "frère",
    "size": 1278
  },
  {
    "text": "conférence",
    "size": 1269
  },
  {
    "text": "compte",
    "size": 1265
  },
  {
    "text": "peuple",
    "size": 1256
  },
  {
    "text": "part",
    "size": 1254
  },
  {
    "text": "solidarité",
    "size": 1247
  },
  {
    "text": "comité",
    "size": 1242
  },
  {
    "text": "terroriste",
    "size": 1239
  },
  {
    "text": "centre",
    "size": 1230
  },
  {
    "text": "conseil",
    "size": 1192
  },
  {
    "text": "cheick",
    "size": 1177
  },
  {
    "text": "ailleurs",
    "size": 1176
  },
  {
    "text": "public",
    "size": 1170
  },
  {
    "text": "monsieur",
    "size": 1162
  },
  {
    "text": "pratique",
    "size": 1159
  },
  {
    "text": "entendre",
    "size": 1159
  },
  {
    "text": "vendredi",
    "size": 1150
  },
  {
    "text": "niveau",
    "size": 1150
  },
  {
    "text": "santé",
    "size": 1142
  },
  {
    "text": "projet",
    "size": 1129
  },
  {
    "text": "cadre",
    "size": 1123
  },
  {
    "text": "moyen",
    "size": 1122
  },
  {
    "text": "recevoir",
    "size": 1121
  },
  {
    "text": "bureau",
    "size": 1116
  },
  {
    "text": "enseignement",
    "size": 1099
  },
  {
    "text": "mouton",
    "size": 1095
  },
  {
    "text": "cerfi",
    "size": 1090
  },
  {
    "text": "rencontre",
    "size": 1089
  },
  {
    "text": "bobo",
    "size": 1087
  },
  {
    "text": "rappeler",
    "size": 1079
  },
  {
    "text": "cfa",
    "size": 1077
  },
  {
    "text": "raison",
    "size": 1064
  },
  {
    "text": "mouvement",
    "size": 1063
  },
  {
    "text": "porter",
    "size": 1062
  },
  {
    "text": "arabe",
    "size": 1057
  },
  {
    "text": "sens",
    "size": 1055
  },
  {
    "text": "valeur",
    "size": 1050
  },
  {
    "text": "cérémonie",
    "size": 1037
  },
  {
    "text": "mieux",
    "size": 1035
  },
  {
    "text": "nombre",
    "size": 1035
  },
  {
    "text": "expliquer",
    "size": 1025
  },
  {
    "text": "arriver",
    "size": 1023
  },
  {
    "text": "célébrer",
    "size": 1016
  },
  {
    "text": "nation",
    "size": 1007
  },
  {
    "text": "ville",
    "size": 1000
  },
  {
    "text": "charge",
    "size": 998
  },
  {
    "text": "important",
    "size": 994
  },
  {
    "text": "accomplir",
    "size": 993
  },
  {
    "text": "voyage",
    "size": 989
  },
  {
    "text": "thème",
    "size": 987
  },
  {
    "text": "afrique",
    "size": 985
  },
  {
    "text": "représentant",
    "size": 982
  },
  {
    "text": "éducation",
    "size": 981
  },
  {
    "text": "agence",
    "size": 980
  },
  {
    "text": "meilleur",
    "size": 978
  },
  {
    "text": "commission",
    "size": 977
  },
  {
    "text": "rapport",
    "size": 976
  },
  {
    "text": "croyant",
    "size": 973
  },
  {
    "text": "mission",
    "size": 971
  },
  {
    "text": "mesure",
    "size": 971
  },
  {
    "text": "humain",
    "size": 967
  },
  {
    "text": "arabie",
    "size": 966
  },
  {
    "text": "oeuvre",
    "size": 959
  },
  {
    "text": "attendre",
    "size": 954
  },
  {
    "text": "message",
    "size": 953
  },
  {
    "text": "objectif",
    "size": 947
  },
  {
    "text": "tabaski",
    "size": 947
  },
  {
    "text": "recherche",
    "size": 943
  },
  {
    "text": "attaque",
    "size": 942
  },
  {
    "text": "condition",
    "size": 939
  },
  {
    "text": "al",
    "size": 939
  },
  {
    "text": "cause",
    "size": 937
  },
  {
    "text": "province",
    "size": 936
  },
  {
    "text": "saoudite",
    "size": 935
  },
  {
    "text": "cohésion",
    "size": 925
  },
  {
    "text": "présence",
    "size": 922
  },
  {
    "text": "grâce",
    "size": 915
  },
  {
    "text": "exemple",
    "size": 914
  },
  {
    "text": "dialogue",
    "size": 912
  },
  {
    "text": "inviter",
    "size": 905
  },
  {
    "text": "spirituel",
    "size": 905
  },
  {
    "text": "croire",
    "size": 904
  },
  {
    "text": "suite",
    "size": 902
  },
  {
    "text": "international",
    "size": 900
  },
  {
    "text": "prix",
    "size": 898
  },
  {
    "text": "face",
    "size": 895
  },
  {
    "text": "lutte",
    "size": 892
  },
  {
    "text": "fédération",
    "size": 889
  },
  {
    "text": "ministère",
    "size": 883
  }
]